forgeconf/__init__.py
forgeconf-0.0.0a0.dist-info/licenses/LICENSE
forgeconf-0.0.0a0.dist-info/METADATA
forgeconf-0.0.0a0.dist-info/WHEEL
forgeconf-0.0.0a0.dist-info/entry_points.txt
forgeconf-0.0.0a0.dist-info/top_level.txt
forgeconf-0.0.0a0.dist-info/RECORD
