Metadata-Version: 2.4
Name: forgeconf
Version: 0.0.0a0
Summary: ForgeConf: Adaptive, type-safe configuration management.
Author-email: "mesotron.dev" <mail@mesotron.dev>
Maintainer-email: "mesotron.dev" <mail@mesotron.dev>
License:                                  Apache License
Project-URL: Homepage, https://mesotron.dev/deployments/forgeconf
Project-URL: Repository, https://github.com/nortosem/forgeconf
Keywords: configuration,gcp,django,fastapi,settings,deployment
Classifier: Development Status :: 2 - Pre-Alpha
Classifier: Intended Audience :: Developers
Classifier: Operating System :: OS Independent
Classifier: License :: OSI Approved :: Apache Software License
Classifier: Programming Language :: Python :: 3
Classifier: Topic :: Software Development :: Libraries :: Python Modules
Requires-Python: >=3.13
License-File: LICENSE
Requires-Dist: click
Requires-Dist: google-auth>=2.40.0
Requires-Dist: PyYAML>=6.0.2
Requires-Dist: requests>=2.32.4
Requires-Dist: rich>=14.0.0
Requires-Dist: toml>=0.10.2
Provides-Extra: dev
Requires-Dist: coverage[toml]>=7.5.0; extra == "dev"
Requires-Dist: mypy~=1.16.1; extra == "dev"
Requires-Dist: mypy_extensions>=1.0.0; extra == "dev"
Requires-Dist: pip-tools>=7.4.1; extra == "dev"
Requires-Dist: pytest>=8.0; extra == "dev"
Requires-Dist: pytest-mock>=3.14; extra == "dev"
Requires-Dist: ruff>=0.12; extra == "dev"
Requires-Dist: build>=1.2.1; extra == "dev"
Requires-Dist: twine>=5.1.1; extra == "dev"
Requires-Dist: keyring>=25.2.1; extra == "dev"
Requires-Dist: keyrings.google-artifactregistry-auth>=1.1.2; extra == "dev"
Requires-Dist: types-requests>=2.32.4.20250611; extra == "dev"
Dynamic: license-file
